csv2anki/__init__.py
csv2anki/__main__.py
csv2anki/cli.py
csv2anki/collection.py
csv2anki/db.py
csv2anki-0.0.3.dist-info/DESCRIPTION.rst
csv2anki-0.0.3.dist-info/METADATA
csv2anki-0.0.3.dist-info/RECORD
csv2anki-0.0.3.dist-info/WHEEL
csv2anki-0.0.3.dist-info/entry_points.txt
csv2anki-0.0.3.dist-info/metadata.json
csv2anki-0.0.3.dist-info/top_level.txt
