Metadata-Version: 2.0
Name: csv2anki
Version: 0.0.3
Summary: A Anki decks generator
Home-page: https://github.com/albertix/csv2anki
Author: albertix
Author-email: albertix@live.com
License: AGPL
Keywords: anki
Platform: UNKNOWN
Classifier: Development Status :: 3 - Alpha
Classifier: Intended Audience :: Developers
Classifier: Topic :: Software Development :: Build Tools
Classifier: License :: OSI Approved :: GNU Affero General Public License v3 or later (AGPLv3+)
Classifier: Programming Language :: Python :: 3
Classifier: Programming Language :: Python :: 3.5
Classifier: Programming Language :: Python :: 3.6
Requires-Dist: chardet
Requires-Dist: click
Provides-Extra: test
Requires-Dist: pytest; extra == 'test'
